srt_deepl/__init__.py
srt_deepl/__main__.py
srt_deepl/deepl.py
srt_deepl/elements.py
srt_deepl/main.py
srt_deepl/srt_parser.py
srt_deepl/utils.py
test/__init__.py
test/test_srt_parser.py
srt_deepl-0.9.1.dist-info/LICENSE.md
srt_deepl-0.9.1.dist-info/METADATA
srt_deepl-0.9.1.dist-info/WHEEL
srt_deepl-0.9.1.dist-info/top_level.txt
srt_deepl-0.9.1.dist-info/RECORD
