Metadata-Version: 2.1
Name: srt-deepl
Version: 0.9.1
Summary: Traslate a .SRT file using DeepL and Selenium.
Home-page: https://github.com/sinedie/SRT-DeepL-Translator
Author: EAR
Author-email: sinedie@protonmail.com
License: FREE
Keywords: python,srt,deepl,languages,translator,subtitles
Platform: UNKNOWN
Classifier: Development Status :: 1 - Planning
Classifier: Intended Audience :: Developers
Classifier: Programming Language :: Python :: 3
Classifier: Operating System :: Unix
Classifier: Operating System :: MacOS :: MacOS X
Classifier: Operating System :: Microsoft :: Windows
Requires-Python: >=3.6
License-File: LICENSE.md
Requires-Dist: easygui (==0.98.2)
Requires-Dist: geckodriver-autoinstaller (==0.1.0)
Requires-Dist: selenium (==3.141.0)
Requires-Dist: srt (==3.4.1)
Requires-Dist: urllib3 (==1.26.5)
